<?xml version="1.0" encoding="UTF-8"?>
<AutoItems>
	
    <item itemKey ="application.commercialClaimTimes"  name="上年商业理赔次数">
    	<condition1  code="others.noClaimDiscountCoefficient"  name ="无赔款优待系数" value="0.7"/>
    		<condition2 code="application.commercial.claimTimes"  name ="商业险理赔总次数" value="0"/>
    				<result value ="-2"  resultName="连续三年没有理赔" />			
    </item>
    
      <item itemKey ="application.commercialClaimTimes"  name="上年商业理赔次数">
    	<condition1  code="others.noClaimDiscountCoefficient"  name ="无赔款优待系数" value="0.8"/>
    		<condition2 code="application.commercial.claimTimes"  name ="商业险理赔总次数" value="0"/>
    				<result value ="-1"  resultName="连续两年没有理赔" /> 
    </item>
    
      <item itemKey ="application.commercialClaimTimes"  name="上年商业理赔次数">
    	<condition1  code="others.noClaimDiscountCoefficient"  name ="无赔款优待系数" value="0.9"/>
    		<condition2 code="application.commercial.claimTimes"  name ="商业险理赔总次数" value="0"/>
    				<result value ="0"  resultName="去年没有理赔" /> 
    </item>
    
      <item itemKey ="application.commercialClaimTimes"  name="上年商业理赔次数">
    	<condition1  code="others.noClaimDiscountCoefficient"  name ="无赔款优待系数" value="1.0"/>
    		<condition2 code="application.commercial.claimTimes"  name ="商业险理赔总次数" value="1"/>
    				<result value ="1"  resultName="去年发生一次理赔" />  
    </item>
    
      <item itemKey ="application.commercialClaimTimes"  name="上年商业理赔次数">
    	<condition1  code="others.noClaimDiscountCoefficient"  name ="无赔款优待系数" value="1.0"/>
    		<condition2 code="application.commercial.claimTimes"  name ="商业险理赔总次数" value="2"/>
    				<result value ="2"  resultName="去年发生两次理赔" />   
    </item>
    
      <item itemKey ="application.commercialClaimTimes"  name="上年商业理赔次数">
    	<condition1  code="others.noClaimDiscountCoefficient"  name ="无赔款优待系数" value="1.1"/>
    		<condition2 code="application.commercial.claimTimes"  name ="商业险理赔总次数" value="0"/>
    				<result value ="3"  resultName="去年发生三次理赔" />
    </item>
    
      <item itemKey ="application.commercialClaimTimes"  name="上年商业理赔次数">
    	<condition1  code="others.noClaimDiscountCoefficient"  name ="无赔款优待系数" value="1.2"/>
    		<condition2 code="application.commercial.claimTimes"  name ="商业险理赔总次数" value="0"/>
    				<result value ="4"  resultName="去年发生四次理赔" />  
    </item>
    
      <item itemKey ="application.commercialClaimTimes"  name="上年商业理赔次数">
    	<condition1  code="others.noClaimDiscountCoefficient"  name ="无赔款优待系数" value="1.3"/>
    		<condition2 code="application.commercial.claimTimes"  name ="商业险理赔总次数" value="0"/>
    				<result value ="5"  resultName="去年发生五次理赔" />   
    </item>
    
     
    
      <item itemKey ="application.firstInsureType"  name="投保类型">
    	<condition1  code="application.loyalty"  name ="客户忠诚度系数" value="0.9"/>    		
    				<result value ="0"  resultName="非首次投保" />    			
    </item>
    
         <item itemKey ="application.compulsoryClaimTimes"  name="上年交强理赔次数">
    	<condition1  code="application.compulsory.claimRate"  name ="交强险理赔系数" value="0.7"/>    		
    				<result value ="-2"  resultName="连续三年没有理赔" />    			   
    </item>
    
         <item itemKey ="application.compulsoryClaimTimes"  name="上年交强理赔次数">
    	<condition1  code="application.compulsory.claimRate"  name ="交强险理赔系数" value="0.8"/>    		
    				<result value ="-1"  resultName="连续两年没有理赔" />    			  
    </item>
    
         <item itemKey ="application.compulsoryClaimTimes"  name="上年交强理赔次数">
    	<condition1  code="application.compulsory.claimRate"  name ="交强险理赔系数" value="0.9"/>    		
    				<result value ="0"  resultName="上年没有理赔" />    			 
    </item>
    
         <item itemKey ="application.compulsoryClaimTimes"  name="上年交强理赔次数">
    	<condition1  code="application.compulsoryClaimTimes"  name ="交强险理赔系数" value="1.0"/>    		
    				<result value ="1"  resultName="上年发生一次有责任不涉及死亡理赔或新保" />    			  
    </item>
    
        <item itemKey ="application.compulsoryClaimTimes"  name="上年交强理赔次数">
    	<condition1  code="application.compulsory.claimRate"  name ="交强险理赔系数" value="1.1"/>    		
    				<result value ="2"  resultName="上年有两次及以上理赔" />    			   
    </item>
    
         <item itemKey ="application.compulsoryClaimTimes"  name="上年交强理赔次数">
    	<condition1  code="application.compulsory.claimRate"  name ="交强险理赔系数" value="1.3"/>    		
    				<result value ="3"  resultName="上年有涉及死亡理赔" />    			 
    </item>
    
</AutoItems>